[
    {
        "pk": 1, 
        "model": "myshop.book", 
        "fields": {
            "isbn": "978-0385333481",
            "product_ptr": 1
        }
    }, 
    {
        "pk": 1, 
        "model": "shop.product", 
        "fields": {
            "polymorphic_ctype": ["myshop", "book"],
            "name": "Cat's Cradle: A Novel", 
            "unit_price": "9.99", 
            "slug": "cats-cradle", 
            "active": true, 
            "last_modified": "2011-03-03 07:06:08", 
            "date_added": "2011-03-03 07:06:08" 
        }
    }, 
    {
        "pk": 1, 
        "model": "addressmodel.country", 
        "fields": {
            "name": "USA"
        }
    }


]
